[
  {
    "id": "m-1784645580758",
    "name": "آرت ۱",
    "issue": "",
    "tags": [],
    "cover": "https://cdn.imgurl.ir/uploads/t4857_002-IMG_20260720_223342_133.jpg",
    "download": "https://cdn.imgurl.ir/uploads/t4857_002-IMG_20260720_223342_133.jpg",
    "description": "آرت",
    "active": true,
    "views": 4,
    "featured": false,
    "addedBy": "مدیر کل",
    "pending": true,
    "guestEmail": "silverspark.ir@gmail.com",
    "guestName": "حسن",
    "guestCode": "VEN-uRzRg52N",
    "salesCount": 2,
    "totalEarnings": 15000
  }
]