[
  {
    "id": "user-1784160446847",
    "itemType": "تمبر",
    "name": "تمبر قاجار",
    "price": 2000000,
    "year": "",
    "country": "",
    "image1": "https://cdn.imgurl.ir/uploads/e565532_Screenshot_------_files.fileexorer.jpg",
    "image2": "",
    "image3": "",
    "description": "تمبر احمدشاه قاجار",
    "active": true,
    "views": 0,
    "createdAt": "2026-07-16T00:07:26.847Z",
    "sellerAccessCode": "STPS2026ADMINKEY001",
    "sellerPostalCode": "7424123215",
    "discountRequests": [
      {
        "name": "ادمین",
        "price": 1500000,
        "time": "2026-07-16T00:09:51.345Z"
      }
    ],
    "purchaseRequest": null,
    "purchaseVerified": false,
    "sellerPaid": false
  }
]